leap/__init__.py
leap/pixelated/__init__.py
leap/pixelated/account_recovery.py
leap/pixelated/application.py
leap/pixelated/authentication.py
leap/pixelated/maintenance.py
leap/pixelated/register.py
leap/pixelated/adapter/__init__.py
leap/pixelated/adapter/welcome_mail.py
leap/pixelated/adapter/listeners/__init__.py
leap/pixelated/adapter/listeners/mailbox_indexer_listener.py
leap/pixelated/adapter/mailstore/__init__.py
leap/pixelated/adapter/mailstore/body_parser.py
leap/pixelated/adapter/mailstore/leap_attachment_store.py
leap/pixelated/adapter/mailstore/leap_mailstore.py
leap/pixelated/adapter/mailstore/mailstore.py
leap/pixelated/adapter/mailstore/searchable_mailstore.py
leap/pixelated/adapter/mailstore/maintenance/__init__.py
leap/pixelated/adapter/model/__init__.py
leap/pixelated/adapter/model/mail.py
leap/pixelated/adapter/model/status.py
leap/pixelated/adapter/model/tag.py
leap/pixelated/adapter/search/__init__.py
leap/pixelated/adapter/search/contacts.py
leap/pixelated/adapter/search/index_storage_key.py
leap/pixelated/adapter/services/__init__.py
leap/pixelated/adapter/services/draft_service.py
leap/pixelated/adapter/services/feedback_service.py
leap/pixelated/adapter/services/mail_sender.py
leap/pixelated/adapter/services/mail_service.py
leap/pixelated/adapter/services/tag_service.py
leap/pixelated/assets/__init__.py
leap/pixelated/bitmask_libraries/__init__.py
leap/pixelated/bitmask_libraries/certs.py
leap/pixelated/bitmask_libraries/keymanager.py
leap/pixelated/bitmask_libraries/provider.py
leap/pixelated/bitmask_libraries/smtp.py
leap/pixelated/certificates/__init__.py
leap/pixelated/config/__init__.py
leap/pixelated/config/arguments.py
leap/pixelated/config/credentials.py
leap/pixelated/config/leap.py
leap/pixelated/config/leap_config.py
leap/pixelated/config/logger.py
leap/pixelated/config/services.py
leap/pixelated/config/sessions.py
leap/pixelated/config/site.py
leap/pixelated/extensions/__init__.py
leap.pixelated-1.0.201709121425.dist-info/DESCRIPTION.rst
leap.pixelated-1.0.201709121425.dist-info/METADATA
leap.pixelated-1.0.201709121425.dist-info/RECORD
leap.pixelated-1.0.201709121425.dist-info/WHEEL
leap.pixelated-1.0.201709121425.dist-info/metadata.json
leap.pixelated-1.0.201709121425.dist-info/top_level.txt
