Metadata-Version: 2.0
Name: leap.pixelated
Version: 1.0.201709121425
Summary: Twisted API with a RESTful service for the Pixelated front-end.
Home-page: https://github.com/leapcode/pixelated-user-agent
Author: LEAP Encryption Access Project
Author-email: info@leap.se
License: GNU Affero General Public License v3 or later (AGPLv3+)
Platform: UNKNOWN
Requires-Dist: chardet
Requires-Dist: pyasn1
Requires-Dist: requests
Requires-Dist: twisted
Requires-Dist: whoosh
